config/gssproxy.conf
config/httpd.conf
config/systemd-httpd-service.conf
config/tmpfiles.conf
flask_mod_auth_gssapi/__init__.py
flask_mod_auth_gssapi/ext.py
tests/__init__.py
tests/conftest.py
tests/test_ext.py
tox.ini
flask_mod_auth_gssapi-1.1.1.dist-info/LICENSE
flask_mod_auth_gssapi-1.1.1.dist-info/METADATA
flask_mod_auth_gssapi-1.1.1.dist-info/WHEEL
flask_mod_auth_gssapi-1.1.1.dist-info/RECORD
